pip_check/__init__.py
pip_check/__main__.py
pip_check-3.2.1.dist-info/METADATA
pip_check-3.2.1.dist-info/WHEEL
pip_check-3.2.1.dist-info/entry_points.txt
pip_check-3.2.1.dist-info/licenses/LICENSE
pip_check-3.2.1.dist-info/RECORD
