Metadata-Version: 2.4
Name: pip-check
Version: 3.2.1
Summary: Display installed pip packages and their update status.
Project-URL: Homepage, https://github.com/bartTC/pip-check/
Project-URL: Issues, https://github.com/bartTC/pip-check/issues
Author-email: Martin Mahner <martin@mahner.org>
License: MIT
License-File: LICENSE
Classifier: Development Status :: 5 - Production/Stable
Classifier: Environment :: Console
Classifier: Intended Audience :: Developers
Classifier: License :: OSI Approved :: MIT License
Classifier: Operating System :: OS Independent
Classifier: Programming Language :: Python
Classifier: Programming Language :: Python :: 3.8
Classifier: Programming Language :: Python :: 3.9
Classifier: Programming Language :: Python :: 3.10
Classifier: Programming Language :: Python :: 3.11
Classifier: Programming Language :: Python :: 3.12
Classifier: Programming Language :: Python :: 3.13
Classifier: Programming Language :: Python :: 3.14
Requires-Python: >=3.8
Requires-Dist: packaging
Requires-Dist: terminaltables
